{"cameraMode":{"drawMode":0,"name":"Shaded","section":"Shading Mode"},"sceneLighting":true,"audioPlay":false,"sceneViewState":{"m_AlwaysRefresh":false,"showFog":true,"showSkybox":true,"showFlares":true,"showImageEffects":true,"showParticleSystems":true,"showVisualEffectGraphs":true,"m_FxEnabled":true},"in2DMode":false,"pivot":{"x":34.00259780883789,"y":-15.342758178710938,"z":53.624183654785159},"rotation":{"x":0.3615737557411194,"y":0.30382102727890017,"z":-0.12426318228244782,"w":0.872651219367981},"size":23.40426254272461,"orthographic":false}